tca/__init__.py
tca-0.0.1.dist-info/LICENSE
tca-0.0.1.dist-info/METADATA
tca-0.0.1.dist-info/WHEEL
tca-0.0.1.dist-info/top_level.txt
tca-0.0.1.dist-info/RECORD
