Metadata-Version: 2.1
Name: tca
Version: 0.0.1
Summary: A TCA package
Home-page: https://github.com/ahgnaw/tca
Author: Ana Ruelas
Author-email: anaruelas@gmail.com
License: UNKNOWN
Platform: UNKNOWN
Classifier: Programming Language :: Python :: 3
Classifier: License :: OSI Approved :: MIT License
Classifier: Operating System :: OS Independent
